main.py
weather_mcp_kmy-0.1.0.dist-info/METADATA
weather_mcp_kmy-0.1.0.dist-info/WHEEL
weather_mcp_kmy-0.1.0.dist-info/entry_points.txt
weather_mcp_kmy-0.1.0.dist-info/top_level.txt
weather_mcp_kmy-0.1.0.dist-info/RECORD
